PyOBD/PyOBD.py
PyOBD/__init__.py
pyobd-0.1.8.dist-info/LICENSE
pyobd-0.1.8.dist-info/METADATA
pyobd-0.1.8.dist-info/WHEEL
pyobd-0.1.8.dist-info/top_level.txt
pyobd-0.1.8.dist-info/RECORD
