Metadata-Version: 2.1
Name: pyobd
Version: 0.1.8
Summary: PyOBD - Open BYMA Data API 
Home-page: https://github.com/franco-lamas/PyOBD
Author: Franco Lamas, Nacho Herrera, St1tch
Author-email: francomlamas@gmail.com
License: GPL V3
Keywords: pandas,BYMA,online,historical,downloader,finance
Platform: any
Classifier: License :: OSI Approved :: Apache Software License
Classifier: Development Status :: 3 - Alpha
Classifier: Operating System :: OS Independent
Classifier: Intended Audience :: Developers
Classifier: Topic :: Office/Business :: Financial
Classifier: Topic :: Office/Business :: Financial :: Investment
Classifier: Topic :: Scientific/Engineering :: Interface Engine/Protocol Translator
Classifier: Topic :: Software Development :: Libraries
Classifier: Topic :: Software Development :: Libraries :: Python Modules
Classifier: Programming Language :: Python :: 3
Classifier: Programming Language :: Python :: 3.6
Classifier: Programming Language :: Python :: 3.7
Classifier: Programming Language :: Python :: 3.8
Classifier: Programming Language :: Python :: 3.9
License-File: LICENSE
Requires-Dist: pandas >=1.0.0
Requires-Dist: numpy >=1.18.1
Requires-Dist: requests >=2.21.0
Requires-Dist: datetime >=4.3
Requires-Dist: pytz >=2021.3
Requires-Dist: urllib3
